malfetcher/__init__.py
malfetcher/mal_config_utils.py
malfetcher/mal_fetcher.py
malfetcher/utils.py
malfetcher-2.0.0.dist-info/licenses/LICENSE
malfetcher-2.0.0.dist-info/METADATA
malfetcher-2.0.0.dist-info/WHEEL
malfetcher-2.0.0.dist-info/top_level.txt
malfetcher-2.0.0.dist-info/RECORD
