Metadata-Version: 2.4
Name: malfetcher
Version: 2.0.0
Summary: A simple library to help you fetch data from MyAnimeList.
Author: Dominik Procházka
Maintainer: Dominik Procházka
Project-URL: Homepage, https://github.com/prochy-exe/malfetcher
Project-URL: Documentation, https://github.com/prochy-exe/malfetcher/wiki
Project-URL: Source, https://github.com/prochy-exe/malfetcher
Keywords: python,mal,myanimelist
Classifier: Development Status :: 5 - Production/Stable
Classifier: Framework :: Flask
Classifier: Topic :: Database
Classifier: Topic :: Games/Entertainment
Classifier: License :: OSI Approved :: GNU General Public License v3 or later (GPLv3+)
Classifier: Programming Language :: Python :: 3.8
Classifier: Programming Language :: Python :: 3.9
Classifier: Programming Language :: Python :: 3.10
Classifier: Programming Language :: Python :: 3.11
Classifier: Programming Language :: Python :: 3.12
Requires-Python: >=3.8
License-File: LICENSE
Requires-Dist: requests
Requires-Dist: flask
Requires-Dist: gevent
Dynamic: license-file
